<?xml version="1.0" encoding="utf-8"?>
<!DOCTYPE hibernate-mapping PUBLIC "-//Hibernate/Hibernate Mapping DTD 3.0//EN"
"http://www.hibernate.org/dtd/hibernate-mapping-3.0.dtd">
<!-- 
    Mapping file autogenerated by MyEclipse Persistence Tools
-->
<hibernate-mapping>
    <class name="entity.Address" table="address" catalog="pandong">
        <id name="aid" type="java.lang.Integer">
            <column name="aid" />
            <generator class="identity" />
        </id>
        <many-to-one name="customer" class="entity.Customer" fetch="select">
            <column name="cid">
                <comment>用户ID 外键</comment>
            </column>
        </many-to-one>
        <property name="caddress" type="java.lang.String">
            <column name="cAddress">
                <comment>收件人地址</comment>
            </column>
        </property>
        <property name="name" type="java.lang.String">
            <column name="name">
                <comment>收件人姓名</comment>
            </column>
        </property>
        <property name="phone" type="java.lang.String">
            <column name="phone" length="11">
                <comment>收件人电话</comment>
            </column>
        </property>
        <set name="orderses" inverse="true">
            <key>
                <column name="addressID">
                    <comment>收件人地址ID 外键</comment>
                </column>
            </key>
            <one-to-many class="entity.Orders" />
        </set>
    </class>
</hibernate-mapping>
